{"mIIbxW0r7dEZSbMPwcoYdg==":"background2.jpg","9UgKGalXizbs1suQ2ulsdQ==":"background4.jpeg","tDwncyWpsEJ/9VQKhDmW/g==":"49855583_1932269003585208_7498534465229029376_n-724x960.jpg","BgvkEBvUbvx+NvpirEUNXg==":"49855583_1932269003585208_7498534465229029376_n-1-724x960.jpg","d7sLe8C+eUL03ChsYV+5cw==":"49855583_1932269003585208_7498534465229029376_n-1-724x960.jpeg","2/FGucy1R/XLXwJO5QQaTg==":"ador-225x225.png","GVJiwtQptLCqjgvPynQQvQ==":"fmcsa-240x160.png","zZ52bvk984w10207c+v9Gw==":"mvtrip-240x181.jpg","75OLHkHBPCQCX2rpp96paA==":"related-motorcarrierservices-64x64.png","/q3k7vBN0ejZ+SYAAQb24A==":"safer-240x311.png","NlhqZ7dQVRZauenlzI4UWw==":"untitled-225x225.png","t3ONha9K3C5aL1zhi0tQLw==":"related-motorcarrierservices-1-64x64.png","R5veGJon/H1c0hLarG69WQ==":"ador%20-%20copy-225x225.png","U92l7XYMgq1jRJ5wYoCLiw==":"mat.bmp-225x294.jpeg","XRbPQM6IWSkYjP7aYW9M3Q==":"dept%20of%20revenue.bmp-225x294.jpeg","mI5WWYpCQCZoeAe89yIHyg==":"motor%20carrier%20system.bmp-388x540.jpeg","Ok1WPr5IByKZIVgQClYDmA==":"fmcsa@.bmp-275x197.jpeg","51ip0mcbKReu/n5l/dMesw==":"safer2-298x386.jpeg","ikRDHR8FhD2SmAKihrlBMw==":"alts-200x246.jpeg","1gwN6nWpvamrjWx/Jnl8IQ==":"mv%20license%20portal.bmp-259x195.jpeg","pJyr58XqCUNutm7kgs1Pnw==":"records%20request%20portal-259x213.jpeg","eExyHwMuNALFv+/lJv77DQ==":"mv%20license%20portal.bmp-259x195.jpeg","vSTP5P6RiOaXsnT7CU19OQ==":"mv%20license%20portal.bmp-259x195.jpg","bHQMoyXX32xaihUDJDnwuQ==":"mvtrip-259x213.jpg","XNhAGeW7zxx1wwdeJ1Buiw==":"mat.bmp-225x294.jpg","4D0KHN3AmkIxfn5trzhaxQ==":"alabama%20title%20system-200x188.png","mzCg1MIK3GdWcU/3edjWzg==":"alabama%20title%20system-200x234.png","NJA7H/zkBGtNfEXcZf2Dvw==":"records%20request%20portal-259x213.png","G1zZroAxGOc2huKz22XpCA==":"safer2-298x386.png","Zr2Gnknf+wWI2WhPMVWLoQ==":"dept%20of%20revenue-225x294.png","/tQq0zenxiQOhGTvjoVV9g==":"motor%20carrier%20system-388x540.png","4svdT+qKGNKOILXUbVcr3A==":"fmcsa-275x197.png","DUHd2nwSHld53iVBDisuRA==":"public%20title%20portal-98x125.png","7yJSOr92ZNCYG7lU8ahJpw==":"record%20request-120x93.png","9ZO5hSCwgSAE883FIRk1Jg==":"motor%20vehicle%20license-123x102.png","mLuSa0QqLriNI9mPYQShFw==":"motor%20vehicle%20license-123x102.png","xmm+/yT4kiH0Fm41Bdtd1g==":"motor%20vehicle%20license-176x150.jpg","eAfbZ84yaCpuaqdkJ3fJlg==":"record%20request-214x166.jpg","aZFHxzyCuoupKUwDdAuaJw==":"public%20title%20portal-196x250.jpg","4D591cj9nB9Be49kx6+f0Q==":"motor%20vehicle%20license-188x220.jpg","iAqv6nOfHAR4l0NfxWpvSg==":"dept%20of%20revenue.bmp-225x294.jpg","xw4TZWpB3natz0aNPGqUbA==":"motor%20carrier%20system.bmp-240x334.jpg","XLHB9U3Si2oXSFkMMbaISg==":"fmcsa@.bmp-240x172.jpg","yQ5NOlq76tIneiY4h7SHmg==":"safer2-240x311.jpg","kYnNgRLcfxcjV9+9WxGRBQ==":"mvtrip-240x197.jpg","gsmi/TaoIphVwHOKCFAe9g==":"record%20request-240x186.jpg"}